yestalker_math/__init__.py
yestalker_math/yestalker_math.py
yestalker_math-0.1.0.dist-info/METADATA
yestalker_math-0.1.0.dist-info/WHEEL
yestalker_math-0.1.0.dist-info/licenses/LICENSE
yestalker_math-0.1.0.dist-info/RECORD
